{
    "$schema": "https://vega.github.io/schema/vega-lite/v5.json",
    "data": {
      "values": [
        {"Date": "28/07/1975", "Country": "UK", "Interest Rate": 11},
        {"Date": "28/07/1975", "Country": "US", "Interest Rate": 6.1},
        {"Date": "06/10/1975", "Country": "UK", "Interest Rate": 12},
        {"Date": "06/10/1975", "Country": "US", "Interest Rate": 5.82},
        {"Date": "17/11/1975", "Country": "UK", "Interest Rate": 11.75},
        {"Date": "17/11/1975", "Country": "US", "Interest Rate": 5.22},
        {"Date": "01/12/1975", "Country": "UK", "Interest Rate": 11.5},
        {"Date": "01/12/1975", "Country": "US", "Interest Rate": 5.2},
        {"Date": "29/12/1975", "Country": "UK", "Interest Rate": 11.25},
        {"Date": "29/12/1975", "Country": "US", "Interest Rate": 5.2},
        {"Date": "05/01/1976", "Country": "UK", "Interest Rate": 11},
        {"Date": "05/01/1976", "Country": "US", "Interest Rate": 4.87},
        {"Date": "19/01/1976", "Country": "UK", "Interest Rate": 10.75},
        {"Date": "19/01/1976", "Country": "US", "Interest Rate": 4.87},
        {"Date": "26/01/1976", "Country": "UK", "Interest Rate": 10.5},
        {"Date": "26/01/1976", "Country": "US", "Interest Rate": 4.87},
        {"Date": "02/02/1976", "Country": "UK", "Interest Rate": 10},
        {"Date": "02/02/1976", "Country": "US", "Interest Rate": 4.77},
        {"Date": "09/02/1976", "Country": "UK", "Interest Rate": 9.5},
        {"Date": "09/02/1976", "Country": "US", "Interest Rate": 4.77},
        {"Date": "01/03/1976", "Country": "UK", "Interest Rate": 9.25},
        {"Date": "01/03/1976", "Country": "US", "Interest Rate": 4.84},
        {"Date": "08/03/1976", "Country": "UK", "Interest Rate": 9},
        {"Date": "08/03/1976", "Country": "US", "Interest Rate": 4.84},
        {"Date": "26/04/1976", "Country": "UK", "Interest Rate": 10.5},
        {"Date": "26/04/1976", "Country": "US", "Interest Rate": 4.82},
        {"Date": "24/05/1976", "Country": "UK", "Interest Rate": 11.5},
        {"Date": "24/05/1976", "Country": "US", "Interest Rate": 5.29},
        {"Date": "13/09/1976", "Country": "UK", "Interest Rate": 13},
        {"Date": "13/09/1976", "Country": "US", "Interest Rate": 5.25},
        {"Date": "07/10/1976", "Country": "UK", "Interest Rate": 15},
        {"Date": "07/10/1976", "Country": "US", "Interest Rate": 5.02},
        {"Date": "22/11/1976", "Country": "UK", "Interest Rate": 14.75},
        {"Date": "22/11/1976", "Country": "US", "Interest Rate": 4.95},
        {"Date": "20/12/1976", "Country": "UK", "Interest Rate": 14.5},
        {"Date": "20/12/1976", "Country": "US", "Interest Rate": 4.65},
        {"Date": "29/12/1976", "Country": "UK", "Interest Rate": 14.25},
        {"Date": "29/12/1976", "Country": "US", "Interest Rate": 4.65},
        {"Date": "10/01/1977", "Country": "UK", "Interest Rate": 14},
        {"Date": "10/01/1977", "Country": "US", "Interest Rate": 4.61},
        {"Date": "24/01/1977", "Country": "UK", "Interest Rate": 13.25},
        {"Date": "24/01/1977", "Country": "US", "Interest Rate": 4.61},
        {"Date": "31/01/1977", "Country": "UK", "Interest Rate": 12.25},
        {"Date": "31/01/1977", "Country": "US", "Interest Rate": 4.61},
        {"Date": "03/02/1977", "Country": "UK", "Interest Rate": 12},
        {"Date": "03/02/1977", "Country": "US", "Interest Rate": 4.68},
        {"Date": "10/03/1977", "Country": "UK", "Interest Rate": 11},
        {"Date": "10/03/1977", "Country": "US", "Interest Rate": 4.69},
        {"Date": "21/03/1977", "Country": "UK", "Interest Rate": 10.5},
        {"Date": "21/03/1977", "Country": "US", "Interest Rate": 4.69},
        {"Date": "31/03/1977", "Country": "UK", "Interest Rate": 9.5},
        {"Date": "31/03/1977", "Country": "US", "Interest Rate": 4.69},
        {"Date": "12/04/1977", "Country": "UK", "Interest Rate": 9.25},
        {"Date": "12/04/1977", "Country": "US", "Interest Rate": 4.73},
        {"Date": "18/04/1977", "Country": "UK", "Interest Rate": 9},
        {"Date": "18/04/1977", "Country": "US", "Interest Rate": 4.73},
        {"Date": "25/04/1977", "Country": "UK", "Interest Rate": 8.75},
        {"Date": "25/04/1977", "Country": "US", "Interest Rate": 4.73},
        {"Date": "02/05/1977", "Country": "UK", "Interest Rate": 8.25},
        {"Date": "02/05/1977", "Country": "US", "Interest Rate": 5.35},
        {"Date": "16/05/1977", "Country": "UK", "Interest Rate": 8},
        {"Date": "16/05/1977", "Country": "US", "Interest Rate": 5.35},
        {"Date": "08/08/1977", "Country": "UK", "Interest Rate": 7.5},
        {"Date": "08/08/1977", "Country": "US", "Interest Rate": 5.9},
        {"Date": "15/08/1977", "Country": "UK", "Interest Rate": 7},
        {"Date": "15/08/1977", "Country": "US", "Interest Rate": 5.9},
        {"Date": "12/09/1977", "Country": "UK", "Interest Rate": 6.5},
        {"Date": "12/09/1977", "Country": "US", "Interest Rate": 6.14},
        {"Date": "19/09/1977", "Country": "UK", "Interest Rate": 6},
        {"Date": "19/09/1977", "Country": "US", "Interest Rate": 6.14},
        {"Date": "10/10/1977", "Country": "UK", "Interest Rate": 5.5},
        {"Date": "10/10/1977", "Country": "US", "Interest Rate": 6.47},
        {"Date": "17/10/1977", "Country": "UK", "Interest Rate": 5},
        {"Date": "17/10/1977", "Country": "US", "Interest Rate": 6.47},
        {"Date": "28/11/1977", "Country": "UK", "Interest Rate": 7},
        {"Date": "28/11/1977", "Country": "US", "Interest Rate": 6.51},
        {"Date": "09/01/1978", "Country": "UK", "Interest Rate": 6.5},
        {"Date": "09/01/1978", "Country": "US", "Interest Rate": 6.7},
        {"Date": "12/04/1978", "Country": "UK", "Interest Rate": 7.5},
        {"Date": "12/04/1978", "Country": "US", "Interest Rate": 6.89},
        {"Date": "08/05/1978", "Country": "UK", "Interest Rate": 8.75},
        {"Date": "08/05/1978", "Country": "US", "Interest Rate": 7.36},
        {"Date": "15/05/1978", "Country": "UK", "Interest Rate": 9},
        {"Date": "15/05/1978", "Country": "US", "Interest Rate": 7.36},
        {"Date": "08/06/1978", "Country": "UK", "Interest Rate": 10},
        {"Date": "08/06/1978", "Country": "US", "Interest Rate": 7.6},
        {"Date": "09/11/1978", "Country": "UK", "Interest Rate": 12.5},
        {"Date": "09/11/1978", "Country": "US", "Interest Rate": 9.76},
        {"Date": "08/02/1979", "Country": "UK", "Interest Rate": 14},
        {"Date": "08/02/1979", "Country": "US", "Interest Rate": 10.06},
        {"Date": "01/03/1979", "Country": "UK", "Interest Rate": 13},
        {"Date": "01/03/1979", "Country": "US", "Interest Rate": 10.09},
        {"Date": "05/04/1979", "Country": "UK", "Interest Rate": 12},
        {"Date": "05/04/1979", "Country": "US", "Interest Rate": 10.01},
        {"Date": "13/06/1979", "Country": "UK", "Interest Rate": 14},
        {"Date": "13/06/1979", "Country": "US", "Interest Rate": 10.29},
        {"Date": "15/11/1979", "Country": "UK", "Interest Rate": 17},
        {"Date": "15/11/1979", "Country": "US", "Interest Rate": 13.18},
        {"Date": "03/07/1980", "Country": "UK", "Interest Rate": 16},
        {"Date": "03/07/1980", "Country": "US", "Interest Rate": 9.03},
        {"Date": "25/11/1980", "Country": "UK", "Interest Rate": 14},
        {"Date": "25/11/1980", "Country": "US", "Interest Rate": 15.85},
        {"Date": "11/03/1981", "Country": "UK", "Interest Rate": 12},
        {"Date": "11/03/1981", "Country": "US", "Interest Rate": 14.7},
        {"Date": "25/08/1981", "Country": "UK", "Interest Rate": 12.69},
        {"Date": "25/08/1981", "Country": "US", "Interest Rate": 17.82},
        {"Date": "15/09/1981", "Country": "UK", "Interest Rate": 14},
        {"Date": "15/09/1981", "Country": "US", "Interest Rate": 15.87},
        {"Date": "12/10/1981", "Country": "UK", "Interest Rate": 15},
        {"Date": "12/10/1981", "Country": "US", "Interest Rate": 15.08},
        {"Date": "28/10/1981", "Country": "UK", "Interest Rate": 15.13},
        {"Date": "28/10/1981", "Country": "US", "Interest Rate": 15.08},
        {"Date": "06/11/1981", "Country": "UK", "Interest Rate": 15.06},
        {"Date": "06/11/1981", "Country": "US", "Interest Rate": 13.31},
        {"Date": "09/11/1981", "Country": "UK", "Interest Rate": 14.63},
        {"Date": "09/11/1981", "Country": "US", "Interest Rate": 13.31},
        {"Date": "25/11/1981", "Country": "UK", "Interest Rate": 14.56},
        {"Date": "25/11/1981", "Country": "US", "Interest Rate": 13.31},
        {"Date": "04/12/1981", "Country": "UK", "Interest Rate": 14.38},
        {"Date": "04/12/1981", "Country": "US", "Interest Rate": 12.37},
        {"Date": "18/01/1982", "Country": "UK", "Interest Rate": 14.31},
        {"Date": "18/01/1982", "Country": "US", "Interest Rate": 13.22},
        {"Date": "19/01/1982", "Country": "UK", "Interest Rate": 14.25},
        {"Date": "19/01/1982", "Country": "US", "Interest Rate": 13.22},
        {"Date": "20/01/1982", "Country": "UK", "Interest Rate": 14.13},
        {"Date": "20/01/1982", "Country": "US", "Interest Rate": 13.22},
        {"Date": "21/01/1982", "Country": "UK", "Interest Rate": 14},
        {"Date": "21/01/1982", "Country": "US", "Interest Rate": 13.22},
        {"Date": "22/01/1982", "Country": "UK", "Interest Rate": 13.88},
        {"Date": "22/01/1982", "Country": "US", "Interest Rate": 13.22},
        {"Date": "22/02/1982", "Country": "UK", "Interest Rate": 13.81},
        {"Date": "22/02/1982", "Country": "US", "Interest Rate": 14.78},
        {"Date": "25/02/1982", "Country": "UK", "Interest Rate": 13.63},
        {"Date": "25/02/1982", "Country": "US", "Interest Rate": 14.78},
        {"Date": "10/03/1982", "Country": "UK", "Interest Rate": 13.25},
        {"Date": "10/03/1982", "Country": "US", "Interest Rate": 14.68},
        {"Date": "16/04/1982", "Country": "UK", "Interest Rate": 13.13},
        {"Date": "16/04/1982", "Country": "US", "Interest Rate": 14.94},
        {"Date": "19/04/1982", "Country": "UK", "Interest Rate": 13},
        {"Date": "19/04/1982", "Country": "US", "Interest Rate": 14.94},
        {"Date": "20/04/1982", "Country": "UK", "Interest Rate": 13.13},
        {"Date": "20/04/1982", "Country": "US", "Interest Rate": 14.94},
        {"Date": "08/06/1982", "Country": "UK", "Interest Rate": 12.63},
        {"Date": "08/06/1982", "Country": "US", "Interest Rate": 14.15},
        {"Date": "09/07/1982", "Country": "UK", "Interest Rate": 12.5},
        {"Date": "09/07/1982", "Country": "US", "Interest Rate": 12.59},
        {"Date": "12/07/1982", "Country": "UK", "Interest Rate": 12.25},
        {"Date": "12/07/1982", "Country": "US", "Interest Rate": 12.59},
        {"Date": "13/07/1982", "Country": "UK", "Interest Rate": 12.13},
        {"Date": "13/07/1982", "Country": "US", "Interest Rate": 12.59},
        {"Date": "21/07/1982", "Country": "UK", "Interest Rate": 12.06},
        {"Date": "21/07/1982", "Country": "US", "Interest Rate": 12.59},
        {"Date": "26/07/1982", "Country": "UK", "Interest Rate": 11.94},
        {"Date": "26/07/1982", "Country": "US", "Interest Rate": 12.59},
        {"Date": "28/07/1982", "Country": "UK", "Interest Rate": 11.81},
        {"Date": "28/07/1982", "Country": "US", "Interest Rate": 12.59},
        {"Date": "29/07/1982", "Country": "UK", "Interest Rate": 11.75},
        {"Date": "29/07/1982", "Country": "US", "Interest Rate": 12.59},
        {"Date": "30/07/1982", "Country": "UK", "Interest Rate": 11.63},
        {"Date": "30/07/1982", "Country": "US", "Interest Rate": 12.59},
        {"Date": "02/08/1982", "Country": "UK", "Interest Rate": 11.56},
        {"Date": "02/08/1982", "Country": "US", "Interest Rate": 10.12},
        {"Date": "04/08/1982", "Country": "UK", "Interest Rate": 11.5},
        {"Date": "04/08/1982", "Country": "US", "Interest Rate": 10.12},
        {"Date": "16/08/1982", "Country": "UK", "Interest Rate": 11.38},
        {"Date": "16/08/1982", "Country": "US", "Interest Rate": 10.12},
        {"Date": "17/08/1982", "Country": "UK", "Interest Rate": 11.25},
        {"Date": "17/08/1982", "Country": "US", "Interest Rate": 10.12},
        {"Date": "24/08/1982", "Country": "UK", "Interest Rate": 11.13},
        {"Date": "24/08/1982", "Country": "US", "Interest Rate": 10.12},
        {"Date": "25/08/1982", "Country": "UK", "Interest Rate": 11},
        {"Date": "25/08/1982", "Country": "US", "Interest Rate": 10.12},
        {"Date": "26/08/1982", "Country": "UK", "Interest Rate": 10.88},
        {"Date": "26/08/1982", "Country": "US", "Interest Rate": 10.12},
        {"Date": "27/08/1982", "Country": "UK", "Interest Rate": 10.63},
        {"Date": "27/08/1982", "Country": "US", "Interest Rate": 10.12},
        {"Date": "27/09/1982", "Country": "UK", "Interest Rate": 10.5},
        {"Date": "27/09/1982", "Country": "US", "Interest Rate": 10.31},
        {"Date": "28/09/1982", "Country": "UK", "Interest Rate": 10.38},
        {"Date": "28/09/1982", "Country": "US", "Interest Rate": 10.31},
        {"Date": "29/09/1982", "Country": "UK", "Interest Rate": 10.25},
        {"Date": "29/09/1982", "Country": "US", "Interest Rate": 10.31},
        {"Date": "30/09/1982", "Country": "UK", "Interest Rate": 10.13},
        {"Date": "30/09/1982", "Country": "US", "Interest Rate": 10.31},
        {"Date": "12/10/1982", "Country": "UK", "Interest Rate": 9.63},
        {"Date": "12/10/1982", "Country": "US", "Interest Rate": 9.71},
        {"Date": "01/11/1982", "Country": "UK", "Interest Rate": 9.38},
        {"Date": "01/11/1982", "Country": "US", "Interest Rate": 9.2},
        {"Date": "02/11/1982", "Country": "UK", "Interest Rate": 9.13},
        {"Date": "02/11/1982", "Country": "US", "Interest Rate": 9.2},
        {"Date": "26/11/1982", "Country": "UK", "Interest Rate": 10},
        {"Date": "26/11/1982", "Country": "US", "Interest Rate": 9.2},
        {"Date": "12/01/1983", "Country": "UK", "Interest Rate": 11},
        {"Date": "12/01/1983", "Country": "US", "Interest Rate": 8.68},
        {"Date": "15/03/1983", "Country": "UK", "Interest Rate": 10.56},
        {"Date": "15/03/1983", "Country": "US", "Interest Rate": 8.77},
        {"Date": "13/04/1983", "Country": "UK", "Interest Rate": 10.31},
        {"Date": "13/04/1983", "Country": "US", "Interest Rate": 8.8},
        {"Date": "14/04/1983", "Country": "UK", "Interest Rate": 10.06},
        {"Date": "14/04/1983", "Country": "US", "Interest Rate": 8.8},
        {"Date": "13/06/1983", "Country": "UK", "Interest Rate": 9.81},
        {"Date": "13/06/1983", "Country": "US", "Interest Rate": 8.98},
        {"Date": "14/06/1983", "Country": "UK", "Interest Rate": 9.56},
        {"Date": "14/06/1983", "Country": "US", "Interest Rate": 8.98},
        {"Date": "09/08/1983", "Country": "UK", "Interest Rate": 9.44},
        {"Date": "09/08/1983", "Country": "US", "Interest Rate": 9.56},
        {"Date": "10/08/1983", "Country": "UK", "Interest Rate": 9.56},
        {"Date": "10/08/1983", "Country": "US", "Interest Rate": 9.56},
        {"Date": "03/10/1983", "Country": "UK", "Interest Rate": 9.06},
        {"Date": "03/10/1983", "Country": "US", "Interest Rate": 9.48},
        {"Date": "07/03/1984", "Country": "UK", "Interest Rate": 8.81},
        {"Date": "07/03/1984", "Country": "US", "Interest Rate": 9.91},
        {"Date": "14/03/1984", "Country": "UK", "Interest Rate": 8.56},
        {"Date": "14/03/1984", "Country": "US", "Interest Rate": 9.91},
        {"Date": "10/05/1984", "Country": "UK", "Interest Rate": 9.06},
        {"Date": "10/05/1984", "Country": "US", "Interest Rate": 10.32},
        {"Date": "29/06/1984", "Country": "UK", "Interest Rate": 8.88},
        {"Date": "29/06/1984", "Country": "US", "Interest Rate": 11.06},
        {"Date": "06/07/1984", "Country": "UK", "Interest Rate": 10},
        {"Date": "06/07/1984", "Country": "US", "Interest Rate": 11.23},
        {"Date": "11/07/1984", "Country": "UK", "Interest Rate": 12},
        {"Date": "11/07/1984", "Country": "US", "Interest Rate": 11.23},
        {"Date": "08/08/1984", "Country": "UK", "Interest Rate": 11.5},
        {"Date": "08/08/1984", "Country": "US", "Interest Rate": 11.64},
        {"Date": "09/08/1984", "Country": "UK", "Interest Rate": 11},
        {"Date": "09/08/1984", "Country": "US", "Interest Rate": 11.64},
        {"Date": "16/08/1984", "Country": "UK", "Interest Rate": 10.75},
        {"Date": "16/08/1984", "Country": "US", "Interest Rate": 11.64},
        {"Date": "17/08/1984", "Country": "UK", "Interest Rate": 10.5},
        {"Date": "17/08/1984", "Country": "US", "Interest Rate": 11.64},
        {"Date": "05/11/1984", "Country": "UK", "Interest Rate": 10},
        {"Date": "05/11/1984", "Country": "US", "Interest Rate": 9.43},
        {"Date": "19/11/1984", "Country": "UK", "Interest Rate": 9.75},
        {"Date": "19/11/1984", "Country": "US", "Interest Rate": 9.43},
        {"Date": "23/11/1984", "Country": "UK", "Interest Rate": 9.5},
        {"Date": "23/11/1984", "Country": "US", "Interest Rate": 9.43},
        {"Date": "14/01/1985", "Country": "UK", "Interest Rate": 11.88},
        {"Date": "14/01/1985", "Country": "US", "Interest Rate": 8.35},
        {"Date": "28/01/1985", "Country": "UK", "Interest Rate": 13.88},
        {"Date": "28/01/1985", "Country": "US", "Interest Rate": 8.35},
        {"Date": "20/03/1985", "Country": "UK", "Interest Rate": 13.38},
        {"Date": "20/03/1985", "Country": "US", "Interest Rate": 8.58},
        {"Date": "28/03/1985", "Country": "UK", "Interest Rate": 12.88},
        {"Date": "28/03/1985", "Country": "US", "Interest Rate": 8.58},
        {"Date": "19/04/1985", "Country": "UK", "Interest Rate": 12.38},
        {"Date": "19/04/1985", "Country": "US", "Interest Rate": 8.27},
        {"Date": "11/07/1985", "Country": "UK", "Interest Rate": 11.88},
        {"Date": "11/07/1985", "Country": "US", "Interest Rate": 7.88},
        {"Date": "26/07/1985", "Country": "UK", "Interest Rate": 11.38},
        {"Date": "26/07/1985", "Country": "US", "Interest Rate": 7.88},
        {"Date": "15/01/1986", "Country": "UK", "Interest Rate": 12.38},
        {"Date": "15/01/1986", "Country": "US", "Interest Rate": 8.14},
        {"Date": "19/03/1986", "Country": "UK", "Interest Rate": 11.38},
        {"Date": "19/03/1986", "Country": "US", "Interest Rate": 7.48},
        {"Date": "11/04/1986", "Country": "UK", "Interest Rate": 10.88},
        {"Date": "11/04/1986", "Country": "US", "Interest Rate": 6.99},
        {"Date": "18/04/1986", "Country": "UK", "Interest Rate": 10.38},
        {"Date": "18/04/1986", "Country": "US", "Interest Rate": 6.99},
        {"Date": "23/05/1986", "Country": "UK", "Interest Rate": 9.88},
        {"Date": "23/05/1986", "Country": "US", "Interest Rate": 6.85},
        {"Date": "15/10/1986", "Country": "UK", "Interest Rate": 10.88},
        {"Date": "15/10/1986", "Country": "US", "Interest Rate": 5.85},
        {"Date": "09/03/1987", "Country": "UK", "Interest Rate": 10.38},
        {"Date": "09/03/1987", "Country": "US", "Interest Rate": 6.13},
        {"Date": "18/03/1987", "Country": "UK", "Interest Rate": 9.88},
        {"Date": "18/03/1987", "Country": "US", "Interest Rate": 6.13},
        {"Date": "28/04/1987", "Country": "UK", "Interest Rate": 9.38},
        {"Date": "28/04/1987", "Country": "US", "Interest Rate": 6.37},
        {"Date": "08/05/1987", "Country": "UK", "Interest Rate": 8.88},
        {"Date": "08/05/1987", "Country": "US", "Interest Rate": 6.85},
        {"Date": "06/08/1987", "Country": "UK", "Interest Rate": 9.88},
        {"Date": "06/08/1987", "Country": "US", "Interest Rate": 6.73},
        {"Date": "23/10/1987", "Country": "UK", "Interest Rate": 9.38},
        {"Date": "23/10/1987", "Country": "US", "Interest Rate": 7.29},
        {"Date": "04/11/1987", "Country": "UK", "Interest Rate": 8.88},
        {"Date": "04/11/1987", "Country": "US", "Interest Rate": 6.69},
        {"Date": "03/12/1987", "Country": "UK", "Interest Rate": 8.38},
        {"Date": "03/12/1987", "Country": "US", "Interest Rate": 6.77},
        {"Date": "01/02/1988", "Country": "UK", "Interest Rate": 8.88},
        {"Date": "01/02/1988", "Country": "US", "Interest Rate": 6.58},
        {"Date": "17/03/1988", "Country": "UK", "Interest Rate": 8.38},
        {"Date": "17/03/1988", "Country": "US", "Interest Rate": 6.58},
        {"Date": "08/04/1988", "Country": "UK", "Interest Rate": 7.88},
        {"Date": "08/04/1988", "Country": "US", "Interest Rate": 6.87},
        {"Date": "17/05/1988", "Country": "UK", "Interest Rate": 7.38},
        {"Date": "17/05/1988", "Country": "US", "Interest Rate": 7.09},
        {"Date": "03/06/1988", "Country": "UK", "Interest Rate": 7.88},
        {"Date": "03/06/1988", "Country": "US", "Interest Rate": 7.51},
        {"Date": "10/06/1988", "Country": "UK", "Interest Rate": 8.38},
        {"Date": "10/06/1988", "Country": "US", "Interest Rate": 7.51},
        {"Date": "24/06/1988", "Country": "UK", "Interest Rate": 8.88},
        {"Date": "24/06/1988", "Country": "US", "Interest Rate": 7.51},
        {"Date": "07/07/1988", "Country": "UK", "Interest Rate": 9.88},
        {"Date": "07/07/1988", "Country": "US", "Interest Rate": 7.75},
        {"Date": "21/07/1988", "Country": "UK", "Interest Rate": 10.38},
        {"Date": "21/07/1988", "Country": "US", "Interest Rate": 7.75},
        {"Date": "08/08/1988", "Country": "UK", "Interest Rate": 10.88},
        {"Date": "08/08/1988", "Country": "US", "Interest Rate": 8.01},
        {"Date": "25/08/1988", "Country": "UK", "Interest Rate": 11.88},
        {"Date": "25/08/1988", "Country": "US", "Interest Rate": 8.01},
        {"Date": "25/11/1988", "Country": "UK", "Interest Rate": 12.88},
        {"Date": "25/11/1988", "Country": "US", "Interest Rate": 8.35},
        {"Date": "25/05/1989", "Country": "UK", "Interest Rate": 13.75},
        {"Date": "25/05/1989", "Country": "US", "Interest Rate": 9.81},
        {"Date": "31/08/1989", "Country": "UK", "Interest Rate": 13.84},
        {"Date": "31/08/1989", "Country": "US", "Interest Rate": 8.99},
        {"Date": "04/09/1989", "Country": "UK", "Interest Rate": 13.88},
        {"Date": "04/09/1989", "Country": "US", "Interest Rate": 9.02},
        {"Date": "08/09/1989", "Country": "UK", "Interest Rate": 13.75},
        {"Date": "08/09/1989", "Country": "US", "Interest Rate": 9.02},
        {"Date": "06/10/1989", "Country": "UK", "Interest Rate": 14.88},
        {"Date": "06/10/1989", "Country": "US", "Interest Rate": 8.84},
        {"Date": "08/10/1990", "Country": "UK", "Interest Rate": 13.88},
        {"Date": "08/10/1990", "Country": "US", "Interest Rate": 8.11},
        {"Date": "13/02/1991", "Country": "UK", "Interest Rate": 13.38},
        {"Date": "13/02/1991", "Country": "US", "Interest Rate": 6.25},
        {"Date": "27/02/1991", "Country": "UK", "Interest Rate": 12.88},
        {"Date": "27/02/1991", "Country": "US", "Interest Rate": 6.25},
        {"Date": "22/03/1991", "Country": "UK", "Interest Rate": 12.38},
        {"Date": "22/03/1991", "Country": "US", "Interest Rate": 6.12},
        {"Date": "12/04/1991", "Country": "UK", "Interest Rate": 11.88},
        {"Date": "12/04/1991", "Country": "US", "Interest Rate": 5.91},
        {"Date": "24/05/1991", "Country": "UK", "Interest Rate": 11.38},
        {"Date": "24/05/1991", "Country": "US", "Interest Rate": 5.78},
        {"Date": "12/07/1991", "Country": "UK", "Interest Rate": 10.88},
        {"Date": "12/07/1991", "Country": "US", "Interest Rate": 5.82},
        {"Date": "04/09/1991", "Country": "UK", "Interest Rate": 10.38},
        {"Date": "04/09/1991", "Country": "US", "Interest Rate": 5.45},
        {"Date": "05/05/1992", "Country": "UK", "Interest Rate": 9.88},
        {"Date": "05/05/1992", "Country": "US", "Interest Rate": 3.82},
        {"Date": "22/09/1992", "Country": "UK", "Interest Rate": 8.88},
        {"Date": "22/09/1992", "Country": "US", "Interest Rate": 3.22},
        {"Date": "16/10/1992", "Country": "UK", "Interest Rate": 7.88},
        {"Date": "16/10/1992", "Country": "US", "Interest Rate": 3.1},
        {"Date": "13/11/1992", "Country": "UK", "Interest Rate": 6.88},
        {"Date": "13/11/1992", "Country": "US", "Interest Rate": 3.09},
        {"Date": "26/01/1993", "Country": "UK", "Interest Rate": 5.88},
        {"Date": "26/01/1993", "Country": "US", "Interest Rate": 3.02},
        {"Date": "23/11/1993", "Country": "UK", "Interest Rate": 5.38},
        {"Date": "23/11/1993", "Country": "US", "Interest Rate": 3.02},
        {"Date": "08/02/1994", "Country": "UK", "Interest Rate": 5.13},
        {"Date": "08/02/1994", "Country": "US", "Interest Rate": 3.25},
        {"Date": "12/09/1994", "Country": "UK", "Interest Rate": 5.63},
        {"Date": "12/09/1994", "Country": "US", "Interest Rate": 4.73},
        {"Date": "07/12/1994", "Country": "UK", "Interest Rate": 6.13},
        {"Date": "07/12/1994", "Country": "US", "Interest Rate": 5.45},
        {"Date": "02/02/1995", "Country": "UK", "Interest Rate": 6.63},
        {"Date": "02/02/1995", "Country": "US", "Interest Rate": 5.92},
        {"Date": "13/12/1995", "Country": "UK", "Interest Rate": 6.38},
        {"Date": "13/12/1995", "Country": "US", "Interest Rate": 5.6},
        {"Date": "18/01/1996", "Country": "UK", "Interest Rate": 6.13},
        {"Date": "18/01/1996", "Country": "US", "Interest Rate": 5.56},
        {"Date": "08/03/1996", "Country": "UK", "Interest Rate": 5.94},
        {"Date": "08/03/1996", "Country": "US", "Interest Rate": 5.31},
        {"Date": "06/06/1996", "Country": "UK", "Interest Rate": 5.69},
        {"Date": "06/06/1996", "Country": "US", "Interest Rate": 5.27},
        {"Date": "30/10/1996", "Country": "UK", "Interest Rate": 5.94},
        {"Date": "30/10/1996", "Country": "US", "Interest Rate": 5.24},
        {"Date": "06/05/1997", "Country": "UK", "Interest Rate": 6.25},
        {"Date": "06/05/1997", "Country": "US", "Interest Rate": 5.5},
        {"Date": "06/06/1997", "Country": "UK", "Interest Rate": 6.5},
        {"Date": "06/06/1997", "Country": "US", "Interest Rate": 5.56},
        {"Date": "10/07/1997", "Country": "UK", "Interest Rate": 6.75},
        {"Date": "10/07/1997", "Country": "US", "Interest Rate": 5.52},
        {"Date": "07/08/1997", "Country": "UK", "Interest Rate": 7},
        {"Date": "07/08/1997", "Country": "US", "Interest Rate": 5.54},
        {"Date": "06/11/1997", "Country": "UK", "Interest Rate": 7.25},
        {"Date": "06/11/1997", "Country": "US", "Interest Rate": 5.52},
        {"Date": "04/06/1998", "Country": "UK", "Interest Rate": 7.5},
        {"Date": "04/06/1998", "Country": "US", "Interest Rate": 5.56},
        {"Date": "08/10/1998", "Country": "UK", "Interest Rate": 7.25},
        {"Date": "08/10/1998", "Country": "US", "Interest Rate": 5.07},
        {"Date": "05/11/1998", "Country": "UK", "Interest Rate": 6.75},
        {"Date": "05/11/1998", "Country": "US", "Interest Rate": 4.83},
        {"Date": "10/12/1998", "Country": "UK", "Interest Rate": 6.25},
        {"Date": "10/12/1998", "Country": "US", "Interest Rate": 4.68},
        {"Date": "07/01/1999", "Country": "UK", "Interest Rate": 6},
        {"Date": "07/01/1999", "Country": "US", "Interest Rate": 4.63},
        {"Date": "04/02/1999", "Country": "UK", "Interest Rate": 5.5},
        {"Date": "04/02/1999", "Country": "US", "Interest Rate": 4.76},
        {"Date": "08/04/1999", "Country": "UK", "Interest Rate": 5.25},
        {"Date": "08/04/1999", "Country": "US", "Interest Rate": 4.74},
        {"Date": "10/06/1999", "Country": "UK", "Interest Rate": 5},
        {"Date": "10/06/1999", "Country": "US", "Interest Rate": 4.76},
        {"Date": "08/09/1999", "Country": "UK", "Interest Rate": 5.25},
        {"Date": "08/09/1999", "Country": "US", "Interest Rate": 5.22},
        {"Date": "04/11/1999", "Country": "UK", "Interest Rate": 5.5},
        {"Date": "04/11/1999", "Country": "US", "Interest Rate": 5.42},
        {"Date": "13/01/2000", "Country": "UK", "Interest Rate": 5.75},
        {"Date": "13/01/2000", "Country": "US", "Interest Rate": 5.45},
        {"Date": "10/02/2000", "Country": "UK", "Interest Rate": 6},
        {"Date": "10/02/2000", "Country": "US", "Interest Rate": 5.73},
        {"Date": "08/02/2001", "Country": "UK", "Interest Rate": 5.75},
        {"Date": "08/02/2001", "Country": "US", "Interest Rate": 5.49},
        {"Date": "05/04/2001", "Country": "UK", "Interest Rate": 5.5},
        {"Date": "05/04/2001", "Country": "US", "Interest Rate": 4.8},
        {"Date": "10/05/2001", "Country": "UK", "Interest Rate": 5.25},
        {"Date": "10/05/2001", "Country": "US", "Interest Rate": 4.21},
        {"Date": "02/08/2001", "Country": "UK", "Interest Rate": 5},
        {"Date": "02/08/2001", "Country": "US", "Interest Rate": 3.65},
        {"Date": "18/09/2001", "Country": "UK", "Interest Rate": 4.75},
        {"Date": "18/09/2001", "Country": "US", "Interest Rate": 3.07},
        {"Date": "04/10/2001", "Country": "UK", "Interest Rate": 4.5},
        {"Date": "04/10/2001", "Country": "US", "Interest Rate": 2.49},
        {"Date": "08/11/2001", "Country": "UK", "Interest Rate": 4},
        {"Date": "08/11/2001", "Country": "US", "Interest Rate": 2.09},
        {"Date": "06/02/2003", "Country": "UK", "Interest Rate": 3.75},
        {"Date": "06/02/2003", "Country": "US", "Interest Rate": 1.26},
        {"Date": "10/07/2003", "Country": "UK", "Interest Rate": 3.5},
        {"Date": "10/07/2003", "Country": "US", "Interest Rate": 1.01},
        {"Date": "06/11/2003", "Country": "UK", "Interest Rate": 3.75},
        {"Date": "06/11/2003", "Country": "US", "Interest Rate": 1},
        {"Date": "05/02/2004", "Country": "UK", "Interest Rate": 4},
        {"Date": "05/02/2004", "Country": "US", "Interest Rate": 1.01},
        {"Date": "06/05/2004", "Country": "UK", "Interest Rate": 4.25},
        {"Date": "06/05/2004", "Country": "US", "Interest Rate": 1},
        {"Date": "10/06/2004", "Country": "UK", "Interest Rate": 4.5},
        {"Date": "10/06/2004", "Country": "US", "Interest Rate": 1.03},
        {"Date": "05/08/2004", "Country": "UK", "Interest Rate": 4.75},
        {"Date": "05/08/2004", "Country": "US", "Interest Rate": 1.43},
        {"Date": "04/08/2005", "Country": "UK", "Interest Rate": 4.5},
        {"Date": "04/08/2005", "Country": "US", "Interest Rate": 3.5},
        {"Date": "03/08/2006", "Country": "UK", "Interest Rate": 4.75},
        {"Date": "03/08/2006", "Country": "US", "Interest Rate": 5.25},
        {"Date": "09/11/2006", "Country": "UK", "Interest Rate": 5},
        {"Date": "09/11/2006", "Country": "US", "Interest Rate": 5.25},
        {"Date": "11/01/2007", "Country": "UK", "Interest Rate": 5.25},
        {"Date": "11/01/2007", "Country": "US", "Interest Rate": 5.25},
        {"Date": "10/05/2007", "Country": "UK", "Interest Rate": 5.5},
        {"Date": "10/05/2007", "Country": "US", "Interest Rate": 5.25},
        {"Date": "05/07/2007", "Country": "UK", "Interest Rate": 5.75},
        {"Date": "05/07/2007", "Country": "US", "Interest Rate": 5.26},
        {"Date": "06/12/2007", "Country": "UK", "Interest Rate": 5.5},
        {"Date": "06/12/2007", "Country": "US", "Interest Rate": 4.24},
        {"Date": "07/02/2008", "Country": "UK", "Interest Rate": 5.25},
        {"Date": "07/02/2008", "Country": "US", "Interest Rate": 2.98},
        {"Date": "10/04/2008", "Country": "UK", "Interest Rate": 5},
        {"Date": "10/04/2008", "Country": "US", "Interest Rate": 2.28},
        {"Date": "08/10/2008", "Country": "UK", "Interest Rate": 4.5},
        {"Date": "08/10/2008", "Country": "US", "Interest Rate": 0.97},
        {"Date": "06/11/2008", "Country": "UK", "Interest Rate": 3},
        {"Date": "06/11/2008", "Country": "US", "Interest Rate": 0.39},
        {"Date": "04/12/2008", "Country": "UK", "Interest Rate": 2},
        {"Date": "04/12/2008", "Country": "US", "Interest Rate": 0.16},
        {"Date": "08/01/2009", "Country": "UK", "Interest Rate": 1.5},
        {"Date": "08/01/2009", "Country": "US", "Interest Rate": 0.15},
        {"Date": "05/02/2009", "Country": "UK", "Interest Rate": 1},
        {"Date": "05/02/2009", "Country": "US", "Interest Rate": 0.22},
        {"Date": "05/03/2009", "Country": "UK", "Interest Rate": 0.5},
        {"Date": "05/03/2009", "Country": "US", "Interest Rate": 0.18},
        {"Date": "04/08/2016", "Country": "UK", "Interest Rate": 0.25},
        {"Date": "04/08/2016", "Country": "US", "Interest Rate": 0.4},
        {"Date": "02/11/2017", "Country": "UK", "Interest Rate": 0.5},
        {"Date": "02/11/2017", "Country": "US", "Interest Rate": 1.16},
        {"Date": "02/08/2018", "Country": "UK", "Interest Rate": 0.75},
        {"Date": "02/08/2018", "Country": "US", "Interest Rate": 1.91},
        {"Date": "11/03/2020", "Country": "UK", "Interest Rate": 0.25},
        {"Date": "11/03/2020", "Country": "US", "Interest Rate": 0.65},
        {"Date": "19/03/2020", "Country": "UK", "Interest Rate": 0.1},
        {"Date": "19/03/2020", "Country": "US", "Interest Rate": 0.65},
        {"Date": "16/12/2021", "Country": "UK", "Interest Rate": 0.25},
        {"Date": "16/12/2021", "Country": "US", "Interest Rate": 0.08},
        {"Date": "03/02/2022", "Country": "UK", "Interest Rate": 0.5},
        {"Date": "03/02/2022", "Country": "US", "Interest Rate": 0.08},
        {"Date": "17/03/2022", "Country": "UK", "Interest Rate": 0.75},
        {"Date": "17/03/2022", "Country": "US", "Interest Rate": 0.2},
        {"Date": "05/05/2022", "Country": "UK", "Interest Rate": 1},
        {"Date": "05/05/2022", "Country": "US", "Interest Rate": 0.77},
        {"Date": "16/06/2022", "Country": "UK", "Interest Rate": 1.25},
        {"Date": "16/06/2022", "Country": "US", "Interest Rate": 1.21},
        {"Date": "04/08/2022", "Country": "UK", "Interest Rate": 1.75},
        {"Date": "04/08/2022", "Country": "US", "Interest Rate": 2.33},
        {"Date": "22/09/2022", "Country": "UK", "Interest Rate": 2.25},
        {"Date": "22/09/2022", "Country": "US", "Interest Rate": 2.56}
      ]
    },
    "title": {
      "text": "UK and US Interest Rates",
      "subtitle": "UK and US Interest Rates set by Central Banks (Source: BoE, FRED) ",
      "subtitleFontStyle": "italic",
      "subtitleFontSize": 10,
      "anchor": "start",
      "color": "black"
    },
    "height": 300,
    "width": 300,
    "mark":{"type":"area"},
    "encoding": {
      "x": {"field": "Date", "type": "temporal","axis": {"grid": false}},
      "y": {
        "field": "Interest Rate", 
        "type": "quantitative",
        "scale": {"domain": [0,35]}
        },
      
      "xOffset": {"field": "Country"},
      "color": {"field": "Country"
  }
    }
  }